<?xml version="1.0" encoding="UTF-8"?>
<DEFECTS>
  <DEFECT>
    <SFA>
      <FILEPATH>D:\Proyectos\Clase\PracticasCG\test\</FILEPATH>
      <FILENAME>Camera.cpp</FILENAME>
      <LINE>16</LINE>
      <COLUMN>8</COLUMN>
    </SFA>
    <DEFECTCODE>26495</DEFECTCODE>
    <DESCRIPTION>La variable "Camera::pitch" no está inicializada. Siempre debe inicializarse una variable miembro (type.6).</DESCRIPTION>
    <FUNCTION>Camera::{ctor}</FUNCTION>
    <DECORATED>??0Camera@@QAE@VVector3f@@00PAVSceneObject@@@Z</DECORATED>
    <FUNCLINE>16</FUNCLINE>
    <ADDITIONALINFO>
      <targetSymbol>Camera::pitch</targetSymbol>
    </ADDITIONALINFO>
    <PATH></PATH>
  </DEFECT>
  <DEFECT>
    <SFA>
      <FILEPATH>D:\Proyectos\Clase\PracticasCG\test\</FILEPATH>
      <FILENAME>Camera.cpp</FILENAME>
      <LINE>16</LINE>
      <COLUMN>8</COLUMN>
    </SFA>
    <DEFECTCODE>26495</DEFECTCODE>
    <DESCRIPTION>La variable "Camera::yaw" no está inicializada. Siempre debe inicializarse una variable miembro (type.6).</DESCRIPTION>
    <FUNCTION>Camera::{ctor}</FUNCTION>
    <DECORATED>??0Camera@@QAE@VVector3f@@00PAVSceneObject@@@Z</DECORATED>
    <FUNCLINE>16</FUNCLINE>
    <ADDITIONALINFO>
      <targetSymbol>Camera::yaw</targetSymbol>
    </ADDITIONALINFO>
    <PATH></PATH>
  </DEFECT>
</DEFECTS>